setup.py
client/__init__.py
client/client.py
client/const.py
client/downloader.py
client/uploader.py
client/util.py
grabrc_client.egg-info/PKG-INFO
grabrc_client.egg-info/SOURCES.txt
grabrc_client.egg-info/dependency_links.txt
grabrc_client.egg-info/entry_points.txt
grabrc_client.egg-info/top_level.txt