Metadata-Version: 1.0
Name: grabrc-client
Version: 0.4
Summary: Lightweight, portable Github wrapper. Retrieval of dotfiles (.emacs, .vimrc, etc.) in any environment
Home-page: http://www.github.com/louisrli/grabrc-client/
Author: Louis Li
Author-email: pong@outlook.com
License: UNKNOWN
Platform: UNKNOWN
